tilematrix/__init__.py
tilematrix/_conf.py
tilematrix/_funcs.py
tilematrix/_grid.py
tilematrix/_tile.py
tilematrix/_tilepyramid.py
tilematrix/_types.py
tilematrix/tmx/__init__.py
tilematrix/tmx/main.py
tilematrix-2024.11.0.dist-info/METADATA
tilematrix-2024.11.0.dist-info/WHEEL
tilematrix-2024.11.0.dist-info/entry_points.txt
tilematrix-2024.11.0.dist-info/licenses/LICENSE
tilematrix-2024.11.0.dist-info/RECORD
