Metadata-Version: 2.3
Name: tilematrix
Version: 2024.11.0
Summary: helps handling tile pyramids
Project-URL: Homepage, https://github.com/ungarj/tilematrix
Author-email: Joachim Ungar <joachim.ungar@gmail.com>
License: MIT
Classifier: Development Status :: 5 - Production/Stable
Classifier: Intended Audience :: Developers
Classifier: License :: OSI Approved :: MIT License
Classifier: Programming Language :: Python :: 3.7
Classifier: Programming Language :: Python :: 3.8
Classifier: Programming Language :: Python :: 3.9
Classifier: Programming Language :: Python :: 3.10
Classifier: Topic :: Scientific/Engineering :: GIS
Requires-Dist: affine
Requires-Dist: click
Requires-Dist: geojson
Requires-Dist: rasterio>=1.0.21
Requires-Dist: shapely
Provides-Extra: test
Requires-Dist: black; extra == 'test'
Requires-Dist: coveralls; extra == 'test'
Requires-Dist: flake8; extra == 'test'
Requires-Dist: pre-commit; extra == 'test'
Requires-Dist: pytest; extra == 'test'
Requires-Dist: pytest-cov; extra == 'test'
